[
  {
    "itemid": 1428,
    "minAmount": 1,
    "dropRate": 12,
    "maxAmount": 1
  },
  {
    "itemid": 1391,
    "minAmount": 1,
    "dropRate": 12,
    "maxAmount": 1
  },
  {
    "itemid": 888,
    "minAmount": 15,
    "dropRate": 23,
    "maxAmount": 15
  },
  {
    "itemid": 1432,
    "minAmount": 1,
    "dropRate": 34,
    "maxAmount": 1
  },
  {
    "itemid": 562,
    "minAmount": 4,
    "dropRate": 17,
    "maxAmount": 4
  },
  {
    "itemid": 564,
    "minAmount": 2,
    "dropRate": 17,
    "maxAmount": 2
  },
  {
    "itemid": 563,
    "minAmount": 2,
    "dropRate": 34,
    "maxAmount": 2
  },
  {
    "itemid": 560,
    "minAmount": 2,
    "dropRate": 34,
    "maxAmount": 2
  },
  {
    "itemid": 561,
    "minAmount": 5,
    "dropRate": 34,
    "maxAmount": 5
  },
  {
    "itemid": 561,
    "minAmount": 10,
    "dropRate": 51,
    "maxAmount": 10
  },
  {
    "itemid": 565,
    "minAmount": 2,
    "dropRate": 51,
    "maxAmount": 2
  },
  {
    "itemid": 199,
    "minAmount": 1,
    "dropRate": 23,
    "maxAmount": 1
  },
  {
    "itemid": 201,
    "minAmount": 1,
    "dropRate": 23,
    "maxAmount": 1
  },
  {
    "itemid": 203,
    "minAmount": 1,
    "dropRate": 34,
    "maxAmount": 1
  },
  {
    "itemid": 205,
    "minAmount": 1,
    "dropRate": 34,
    "maxAmount": 1
  },
  {
    "itemid": 209,
    "minAmount": 1,
    "dropRate": 34,
    "maxAmount": 1
  },
  {
    "itemid": 211,
    "minAmount": 1,
    "dropRate": 68,
    "maxAmount": 1
  },
  {
    "itemid": 213,
    "minAmount": 1,
    "dropRate": 68,
    "maxAmount": 1
  },
  {
    "itemid": 207,
    "minAmount": 1,
    "dropRate": 68,
    "maxAmount": 1
  },
  {
    "itemid": 2485,
    "minAmount": 1,
    "dropRate": 102,
    "maxAmount": 1
  },
  {
    "itemid": 217,
    "minAmount": 1,
    "dropRate": 102,
    "maxAmount": 1
  },
  {
    "itemid": 215,
    "minAmount": 1,
    "dropRate": 102,
    "maxAmount": 1
  },
  {
    "itemid": 995,
    "minAmount": 15,
    "dropRate": 9,
    "maxAmount": 15
  },
  {
    "itemid": 2357,
    "minAmount": 1,
    "dropRate": 18,
    "maxAmount": 1
  },
  {
    "itemid": 355,
    "minAmount": 1,
    "dropRate": 26,
    "maxAmount": 1
  },
  {
    "itemid": 1641,
    "minAmount": 1,
    "dropRate": 26,
    "maxAmount": 1
  }
]